qashared/__init__.py
qashared/assertions.py
qashared/fixtures.py
qashared/helpers.py
qashared/hooks.py
qashared/models/__init__.py
qashared/models/base/__init__.py
qashared/models/base/api/__init__.py
qashared/models/base/api/api.py
qashared/models/base/api/route.py
qashared/models/base/ui/__init__.py
qashared/models/base/ui/component.py
qashared/models/base/ui/page.py
qashared/models/extensions/__init__.py
qashared/models/extensions/divido_simple_namespace.py
qashared-0.0.1.dist-info/METADATA
qashared-0.0.1.dist-info/WHEEL
qashared-0.0.1.dist-info/top_level.txt
qashared-0.0.1.dist-info/RECORD
